clive/.clive.py.swp
clive/__init__.py
clive/cli.py
clive/clive.py
clive-0.1.2.dist-info/entry_points.txt
clive-0.1.2.dist-info/LICENSE
clive-0.1.2.dist-info/WHEEL
clive-0.1.2.dist-info/METADATA
clive-0.1.2.dist-info/RECORD
