Metadata-Version: 2.1
Name: clive
Version: 0.1.2
Summary: Follow Reddit live feeds from the comfort of the CLIS
Home-page: https://svenito.github.io/clive/
License: MIT
Author: Sven Steinbauer
Author-email: sven@unlogic.co.uk
Requires-Python: >=3.9,<4.0
Classifier: License :: OSI Approved :: MIT License
Classifier: Programming Language :: Python :: 3
Classifier: Programming Language :: Python :: 3.9
Requires-Dist: colorama (>=0.4.4,<0.5.0)
Requires-Dist: requests (>=2.27.1,<3.0.0)
Requires-Dist: websocket-client (>=1.3.1,<2.0.0)
Project-URL: Repository, https://github.com/Svenito/clive
